{
    "format_version": "1.8.0",
    "minecraft:spawn_rules": {
        "conditions": [
            {
                "minecraft:biome_filter": {
                    "operator": "==",
                    "test": "has_biome_tag",
                    "value": "lush_caves"
                },
                "minecraft:density_limit": {
                    "underground": 5
                },
                "minecraft:permute_type": [
                    {
                        "entity_type": "smokey_bedrock:great_hunger<minecraft:spawn_emerging>",
                        "weight": 1
                    }
                ],
                "minecraft:spawns_on_block_filter": "minecraft:moss_block",
                "minecraft:spawns_underground": {},
                "minecraft:weight": {
                    "default": 100
                }
            }
        ],
        "description": {
            "identifier": "smokey_bedrock:great_hunger",
            "population_control": "animal"
        }
    }
}